spandrel/__init__.py
spandrel/__helpers/__init__.py
spandrel/__helpers/canonicalize.py
spandrel/__helpers/loader.py
spandrel/__helpers/main_registry.py
spandrel/__helpers/model_descriptor.py
spandrel/__helpers/registry.py
spandrel/__helpers/unpickler.py
spandrel/architectures/__init__.py
spandrel/architectures/CRAFT/__init__.py
spandrel/architectures/CRAFT/arch/CRAFT.py
spandrel/architectures/Compact/__init__.py
spandrel/architectures/Compact/arch/SRVGG.py
spandrel/architectures/DAT/__init__.py
spandrel/architectures/DAT/arch/DAT.py
spandrel/architectures/DITN/__init__.py
spandrel/architectures/DITN/arch/DITN_Real.py
spandrel/architectures/ESRGAN/__init__.py
spandrel/architectures/ESRGAN/arch/RRDB.py
spandrel/architectures/FBCNN/__init__.py
spandrel/architectures/FBCNN/arch/FBCNN.py
spandrel/architectures/GRL/__init__.py
spandrel/architectures/GRL/arch/config.py
spandrel/architectures/GRL/arch/grl.py
spandrel/architectures/GRL/arch/mixed_attn_block.py
spandrel/architectures/GRL/arch/mixed_attn_block_efficient.py
spandrel/architectures/GRL/arch/ops.py
spandrel/architectures/GRL/arch/swin_v1_block.py
spandrel/architectures/GRL/arch/upsample.py
spandrel/architectures/HAT/__init__.py
spandrel/architectures/HAT/arch/HAT.py
spandrel/architectures/KBNet/__init__.py
spandrel/architectures/KBNet/arch/kb_utils.py
spandrel/architectures/KBNet/arch/kbnet_l.py
spandrel/architectures/KBNet/arch/kbnet_s.py
spandrel/architectures/LaMa/__init__.py
spandrel/architectures/LaMa/arch/LaMa.py
spandrel/architectures/MMRealSR/__init__.py
spandrel/architectures/MMRealSR/arch/mmrealsr_arch.py
spandrel/architectures/NAFNet/__init__.py
spandrel/architectures/NAFNet/arch/NAFNet_arch.py
spandrel/architectures/NAFNet/arch/arch_util.py
spandrel/architectures/OmniSR/__init__.py
spandrel/architectures/OmniSR/arch/ChannelAttention.py
spandrel/architectures/OmniSR/arch/OSA.py
spandrel/architectures/OmniSR/arch/OSAG.py
spandrel/architectures/OmniSR/arch/OmniSR.py
spandrel_foss-0.2.2.dist-info/LICENSE
spandrel_foss-0.2.2.dist-info/METADATA
spandrel_foss-0.2.2.dist-info/WHEEL
spandrel_foss-0.2.2.dist-info/top_level.txt
spandrel_foss-0.2.2.dist-info/RECORD
