Metadata-Version: 2.1
Name: spandrel-foss
Version: 0.2.2
Summary: Give your project support for a variety of PyTorch model architectures, including auto-detecting model architecture from just .pth files. This version of Spandrel is FOSS compliant as it remove support for model architectures that are under a non-commercial license.
Author: chaiNNer team
License: GPLv3
Keywords: spandrel,pytorch architecture,pytorch arch,model arch,model architecture
Classifier: Development Status :: 2 - Pre-Alpha
Classifier: Intended Audience :: Developers
Classifier: Topic :: Software Development :: Libraries
Classifier: Programming Language :: Python :: 3
Classifier: Programming Language :: Python :: 3.8
Classifier: Programming Language :: Python :: 3.9
Classifier: Programming Language :: Python :: 3.10
Classifier: Programming Language :: Python :: 3.11
Classifier: Programming Language :: Python :: 3.12
Classifier: Programming Language :: Python :: 3 :: Only
Classifier: License :: OSI Approved :: GNU General Public License v3 (GPLv3)
Classifier: Operating System :: OS Independent
Requires-Python: >=3.8
License-File: LICENSE
Requires-Dist: torch
Requires-Dist: torchvision
Requires-Dist: safetensors
Requires-Dist: numpy
Requires-Dist: einops
Requires-Dist: typing-extensions
Provides-Extra: build
Requires-Dist: build ; extra == 'build'
Requires-Dist: twine ; extra == 'build'
Provides-Extra: docs
Requires-Dist: pydoctor ==23.9.1 ; extra == 'docs'
Provides-Extra: lint
Requires-Dist: ruff ==0.1.11 ; extra == 'lint'
Provides-Extra: test
Requires-Dist: pytest ==7.4.0 ; extra == 'test'
Requires-Dist: syrupy ==4.6.0 ; extra == 'test'
Requires-Dist: opencv-python ==4.8.1.78 ; extra == 'test'
Requires-Dist: requests ; extra == 'test'
Requires-Dist: beautifulsoup4 ; extra == 'test'
Provides-Extra: typecheck
Requires-Dist: pyright ==1.1.342 ; extra == 'typecheck'
